PyTator-0.1.4.data/scripts/ingestor.py
PyTator-0.1.4.data/scripts/sendProgress.py
PyTator-0.1.4.data/scripts/tator_testHarness.py
pytator/__init__.py
pytator/api.py
pytator/md5sum.py
pytator/tator.py
pytator/version.py
test/__init__.py
test/_common.py
test/conftest.py
test/test_getframe.py
test/test_localization.py
test/test_media.py
test/test_state.py
test/test_stategraphic.py
test/test_temporary_file.py
test/test_version.py
PyTator-0.1.4.dist-info/LICENSE
PyTator-0.1.4.dist-info/METADATA
PyTator-0.1.4.dist-info/WHEEL
PyTator-0.1.4.dist-info/top_level.txt
PyTator-0.1.4.dist-info/RECORD
