Metadata-Version: 2.1
Name: PyTator
Version: 0.1.4
Summary: Python Bindings for Tator Online REST API
Home-page: http://cvision.tatorapp.com
Author: CVision AI
Author-email: info@cvisionai.com
License: UNKNOWN
Keywords: tator
Platform: UNKNOWN
Classifier: License :: OSI Approved :: MIT License
Requires-Dist: requests (>=2.21.0)
Requires-Dist: progressbar2 (>=3.42.0)
Requires-Dist: tator-tuspy (>=0.2.5)
Requires-Dist: pandas (>=0.24.2)
Requires-Dist: opencv-python (>=4.1.0)
Requires-Dist: numpy (>=1.16.0)
